[
  {
    "full_name": "klis87/normy",
    "stargazers_count": 163,
    "open_issues_count": 13,
    "forks_count": 3
  },
  {
    "full_name": "avgupta456/github-trends",
    "stargazers_count": 10255,
    "open_issues_count": 11,
    "forks_count": 75
  },
  {
    "full_name": "oven-sh/bun",
    "stargazers_count": 70964,
    "open_issues_count": 3169,
    "forks_count": 2463
  },
  {
    "full_name": "meilisearch/meilisearch-js",
    "stargazers_count": 693,
    "open_issues_count": 12,
    "forks_count": 84
  },
  {
    "full_name": "TanStack/router",
    "stargazers_count": 7151,
    "open_issues_count": 25,
    "forks_count": 481
  },
  {
    "full_name": "unjs/nitro",
    "stargazers_count": 5136,
    "open_issues_count": 459,
    "forks_count": 446
  },
  {
    "full_name": "benfred/venn.js",
    "stargazers_count": 1022,
    "open_issues_count": 44,
    "forks_count": 217
  },
  {
    "full_name": "Kanaries/graphic-walker",
    "stargazers_count": 2255,
    "open_issues_count": 16,
    "forks_count": 116
  },
  {
    "full_name": "Kanaries/Rath",
    "stargazers_count": 3997,
    "open_issues_count": 55,
    "forks_count": 292
  },
  {
    "full_name": "yoavbls/pretty-ts-errors",
    "stargazers_count": 12251,
    "open_issues_count": 20,
    "forks_count": 84
  },
  {
    "full_name": "winter-things/winterkit",
    "stargazers_count": 35,
    "open_issues_count": 1,
    "forks_count": 2
  },
  {
    "full_name": "lucaong/minisearch",
    "stargazers_count": 4125,
    "open_issues_count": 7,
    "forks_count": 125
  },
  {
    "full_name": "iway1/react-ts-form",
    "stargazers_count": 2004,
    "open_issues_count": 23,
    "forks_count": 33
  },
  {
    "full_name": "solidjs/solid-start",
    "stargazers_count": 4509,
    "open_issues_count": 41,
    "forks_count": 349
  },
  {
    "full_name": "novuhq/novu",
    "stargazers_count": 33036,
    "open_issues_count": 287,
    "forks_count": 3413
  },
  {
    "full_name": "algolia/docsearch",
    "stargazers_count": 3825,
    "open_issues_count": 128,
    "forks_count": 371
  },
  {
    "full_name": "tw-in-js/twind",
    "stargazers_count": 3696,
    "open_issues_count": 31,
    "forks_count": 96
  },
  {
    "full_name": "TanStack/tanstack.com",
    "stargazers_count": 238,
    "open_issues_count": 24,
    "forks_count": 93
  },
  {
    "full_name": "wmertens/jsurl2",
    "stargazers_count": 78,
    "open_issues_count": 0,
    "forks_count": 3
  },
  {
    "full_name": "evanw/esbuild",
    "stargazers_count": 37359,
    "open_issues_count": 441,
    "forks_count": 1090
  },
  {
    "full_name": "swc-project/swc",
    "stargazers_count": 30097,
    "open_issues_count": 334,
    "forks_count": 1153
  },
  {
    "full_name": "Sage/jsurl",
    "stargazers_count": 375,
    "open_issues_count": 7,
    "forks_count": 30
  },
  {
    "full_name": "nksaraf/magiql",
    "stargazers_count": 199,
    "open_issues_count": 26,
    "forks_count": 1
  },
  {
    "full_name": "lowbyteproductions/Parser-Combinators-From-Scratch",
    "stargazers_count": 85,
    "open_issues_count": 1,
    "forks_count": 8
  },
  {
    "full_name": "pmndrs/jotai",
    "stargazers_count": 17408,
    "open_issues_count": 7,
    "forks_count": 557
  },
  {
    "full_name": "ben-rogerson/twin.macro",
    "stargazers_count": 7809,
    "open_issues_count": 18,
    "forks_count": 184
  },
  {
    "full_name": "SvelteStack/svelte-query",
    "stargazers_count": 811,
    "open_issues_count": 34,
    "forks_count": 31
  },
  {
    "full_name": "JakeChampion/fetch",
    "stargazers_count": 25800,
    "open_issues_count": 8,
    "forks_count": 2847
  },
  {
    "full_name": "bestofjs/bestofjs",
    "stargazers_count": 2550,
    "open_issues_count": 11,
    "forks_count": 139
  },
  {
    "full_name": "discordjs/discord.js",
    "stargazers_count": 24851,
    "open_issues_count": 118,
    "forks_count": 3937
  }
]