[
  {
    "full_name": "algolia/docsearch",
    "stargazers_count": 2687,
    "open_issues_count": 85,
    "forks_count": 245
  },
  {
    "full_name": "tw-in-js/twind",
    "stargazers_count": 2226,
    "open_issues_count": 38,
    "forks_count": 54
  },
  {
    "full_name": "TanStack/tanstack.com",
    "stargazers_count": 51,
    "open_issues_count": 0,
    "forks_count": 9
  },
  {
    "full_name": "wmertens/jsurl2",
    "stargazers_count": 49,
    "open_issues_count": 0,
    "forks_count": 2
  },
  {
    "full_name": "evanw/esbuild",
    "stargazers_count": 32057,
    "open_issues_count": 288,
    "forks_count": 839
  },
  {
    "full_name": "swc-project/swc",
    "stargazers_count": 22451,
    "open_issues_count": 257,
    "forks_count": 720
  },
  {
    "full_name": "Sage/jsurl",
    "stargazers_count": 313,
    "open_issues_count": 7,
    "forks_count": 27
  },
  {
    "full_name": "nksaraf/magiql",
    "stargazers_count": 161,
    "open_issues_count": 26,
    "forks_count": 0
  },
  {
    "full_name": "LowLevelJavaScript/Parser-Combinators-From-Scratch",
    "stargazers_count": 74,
    "open_issues_count": 1,
    "forks_count": 6
  },
  {
    "full_name": "pmndrs/jotai",
    "stargazers_count": 8665,
    "open_issues_count": 34,
    "forks_count": 259
  },
  {
    "full_name": "ben-rogerson/twin.macro",
    "stargazers_count": 5830,
    "open_issues_count": 13,
    "forks_count": 149
  },
  {
    "full_name": "SvelteStack/svelte-query",
    "stargazers_count": 607,
    "open_issues_count": 27,
    "forks_count": 26
  },
  {
    "full_name": "github/fetch",
    "stargazers_count": 25333,
    "open_issues_count": 28,
    "forks_count": 3132
  },
  {
    "full_name": "bestofjs/bestofjs-webui",
    "stargazers_count": 1925,
    "open_issues_count": 11,
    "forks_count": 125
  },
  {
    "full_name": "discordjs/discord.js",
    "stargazers_count": 19524,
    "open_issues_count": 65,
    "forks_count": 3422
  },
  {
    "full_name": "TanStack/virtual",
    "stargazers_count": 2923,
    "open_issues_count": 2,
    "forks_count": 146
  },
  {
    "full_name": "davidkpiano/useEffectReducer",
    "stargazers_count": 767,
    "open_issues_count": 17,
    "forks_count": 21
  },
  {
    "full_name": "BrasilAPI/BrasilAPI",
    "stargazers_count": 4680,
    "open_issues_count": 84,
    "forks_count": 361
  },
  {
    "full_name": "kuldeepkeshwar/size-plugin-bot",
    "stargazers_count": 75,
    "open_issues_count": 20,
    "forks_count": 8
  },
  {
    "full_name": "TanStack/table",
    "stargazers_count": 17638,
    "open_issues_count": 5,
    "forks_count": 2423
  },
  {
    "full_name": "pastelsky/bundlephobia",
    "stargazers_count": 7034,
    "open_issues_count": 268,
    "forks_count": 209
  },
  {
    "full_name": "TanStack/query",
    "stargazers_count": 27744,
    "open_issues_count": 33,
    "forks_count": 1595
  },
  {
    "full_name": "substack/json-stable-stringify",
    "stargazers_count": 654,
    "open_issues_count": 22,
    "forks_count": 104
  },
  {
    "full_name": "davidkpiano/flipping",
    "stargazers_count": 1301,
    "open_issues_count": 21,
    "forks_count": 44
  },
  {
    "full_name": "mike-engel/styled-typography",
    "stargazers_count": 124,
    "open_issues_count": 5,
    "forks_count": 3
  },
  {
    "full_name": "GoogleChrome/rendertron",
    "stargazers_count": 5776,
    "open_issues_count": 95,
    "forks_count": 605
  },
  {
    "full_name": "vercel/next.js",
    "stargazers_count": 87866,
    "open_issues_count": 1224,
    "forks_count": 18741
  },
  {
    "full_name": "cedmax/youmightnotneed",
    "stargazers_count": 127,
    "open_issues_count": 1,
    "forks_count": 22
  },
  {
    "full_name": "d3/d3-scale",
    "stargazers_count": 1450,
    "open_issues_count": 28,
    "forks_count": 283
  },
  {
    "full_name": "sghall/react-vertex",
    "stargazers_count": 1236,
    "open_issues_count": 10,
    "forks_count": 25
  }
]